auth_backends/__init__.py
auth_backends/admin.py
auth_backends/apps.py
auth_backends/models.py
auth_backends/tests.py
auth_backends/views.py
auth_backends/migrations/__init__.py
django_auth_backends-0.0.0.dist-info/METADATA
django_auth_backends-0.0.0.dist-info/WHEEL
django_auth_backends-0.0.0.dist-info/top_level.txt
django_auth_backends-0.0.0.dist-info/RECORD
