Metadata-Version: 2.1
Name: django-auth-backends
Version: 0.0.0
Summary: django auth backends you might need to use
Home-page: http://github.com/lordpeara/django-auth-backends
Author: lordpeara
Author-email: lordpeara@gmail.com
License: MIT
Keywords: django auth authentication backend social-auth ouath2
Platform: UNKNOWN
Requires-Dist: Django (<2.2,>=1.11.21)
